[
  {
    "inputs": [],
    "stateMutability": "nonpayable",
    "type": "constructor"
  },
  {
    "anonymous": false,
    "inputs": [
      {
        "indexed": true,
        "internalType": "address",
        "name": "account",
        "type": "address"
      },
      {
        "indexed": false,
        "internalType": "uint256",
        "name": "amount",
        "type": "uint256"
      }
    ],
    "name": "Airdrop",
    "type": "event"
  },
  {
    "anonymous": false,
    "inputs": [
      {
        "indexed": true,
        "internalType": "address",
        "name": "owner",
        "type": "address"
      },
      {
        "indexed": true,
        "internalType": "address",
        "name": "spender",
        "type": "address"
      },
      {
        "indexed": false,
        "internalType": "uint256",
        "name": "value",
        "type": "uint256"
      }
    ],
    "name": "Approval",
    "type": "event"
  },
  {
    "anonymous": false,
    "inputs": [
      {
        "indexed": false,
        "internalType": "uint256",
        "name": "tokenAdded",
        "type": "uint256"
      },
      {
        "indexed": false,
        "internalType": "uint256",
        "name": "wbnbAdded",
        "type": "uint256"
      }
    ],
    "name": "LiquidityAdded",
    "type": "event"
  },
  {
    "anonymous": false,
    "inputs": [
      {
        "indexed": true,
        "internalType": "address",
        "name": "previousOwner",
        "type": "address"
      },
      {
        "indexed": true,
        "internalType": "address",
        "name": "newOwner",
        "type": "address"
      }
    ],
    "name": "OwnershipTransferred",
    "type": "event"
  },
  {
    "anonymous": false,
    "inputs": [
      {
        "indexed": true,
        "internalType": "address",
        "name": "account",
        "type": "address"
      },
      {
        "indexed": false,
        "internalType": "uint256",
        "name": "bnbAmount",
        "type": "uint256"
      }
    ],
    "name": "PresaleDeposit",
    "type": "event"
  },
  {
    "anonymous": false,
    "inputs": [
      {
        "indexed": false,
        "internalType": "address",
        "name": "account",
        "type": "address"
      }
    ],
    "name": "SlotRegistered",
    "type": "event"
  },
  {
    "anonymous": false,
    "inputs": [
      {
        "indexed": true,
        "internalType": "address",
        "name": "from",
        "type": "address"
      },
      {
        "indexed": true,
        "internalType": "address",
        "name": "to",
        "type": "address"
      },
      {
        "indexed": false,
        "internalType": "uint256",
        "name": "value",
        "type": "uint256"
      }
    ],
    "name": "Transfer",
    "type": "event"
  },
  {
    "anonymous": false,
    "inputs": [
      {
        "indexed": true,
        "internalType": "uint8",
        "name": "txType",
        "type": "uint8"
      },
      {
        "indexed": true,
        "internalType": "address",
        "name": "sender",
        "type": "address"
      },
      {
        "indexed": true,
        "internalType": "address",
        "name": "recipient",
        "type": "address"
      },
      {
        "indexed": false,
        "internalType": "uint256",
        "name": "amount",
        "type": "uint256"
      },
      {
        "indexed": false,
        "internalType": "uint256",
        "name": "txAmount",
        "type": "uint256"
      }
    ],
    "name": "Tx",
    "type": "event"
  },
  {
    "anonymous": false,
    "inputs": [
      {
        "indexed": true,
        "internalType": "address",
        "name": "account",
        "type": "address"
      },
      {
        "indexed": false,
        "internalType": "string",
        "name": "username",
        "type": "string"
      }
    ],
    "name": "UsernameSet",
    "type": "event"
  },
  {
    "stateMutability": "payable",
    "type": "fallback"
  },
  {
    "inputs": [
      {
        "internalType": "uint256",
        "name": "amount",
        "type": "uint256"
      },
      {
        "internalType": "enum HyperDeFiToken.TX_TYPE",
        "name": "txType",
        "type": "uint8"
      }
    ],
    "name": "_txData",
    "outputs": [
      {
        "internalType": "uint256",
        "name": "tax",
        "type": "uint256"
      },
      {
        "internalType": "uint256",
        "name": "airdrop",
        "type": "uint256"
      },
      {
        "internalType": "uint256",
        "name": "fomo",
        "type": "uint256"
      },
      {
        "internalType": "uint256",
        "name": "liquidity",
        "type": "uint256"
      },
      {
        "internalType": "uint256",
        "name": "fund",
        "type": "uint256"
      },
      {
        "internalType": "uint256",
        "name": "destroy",
        "type": "uint256"
      },
      {
        "internalType": "uint256",
        "name": "txAmount",
        "type": "uint256"
      }
    ],
    "stateMutability": "view",
    "type": "function"
  },
  {
    "inputs": [
      {
        "internalType": "address",
        "name": "owner",
        "type": "address"
      },
      {
        "internalType": "address",
        "name": "spender",
        "type": "address"
      }
    ],
    "name": "allowance",
    "outputs": [
      {
        "internalType": "uint256",
        "name": "",
        "type": "uint256"
      }
    ],
    "stateMutability": "view",
    "type": "function"
  },
  {
    "inputs": [
      {
        "internalType": "address",
        "name": "spender",
        "type": "address"
      },
      {
        "internalType": "uint256",
        "name": "amount",
        "type": "uint256"
      }
    ],
    "name": "approve",
    "outputs": [
      {
        "internalType": "bool",
        "name": "",
        "type": "bool"
      }
    ],
    "stateMutability": "nonpayable",
    "type": "function"
  },
  {
    "inputs": [
      {
        "internalType": "address",
        "name": "account",
        "type": "address"
      }
    ],
    "name": "balanceOf",
    "outputs": [
      {
        "internalType": "uint256",
        "name": "",
        "type": "uint256"
      }
    ],
    "stateMutability": "view",
    "type": "function"
  },
  {
    "inputs": [
      {
        "internalType": "uint256",
        "name": "amount",
        "type": "uint256"
      }
    ],
    "name": "burn",
    "outputs": [
      {
        "internalType": "bool",
        "name": "",
        "type": "bool"
      }
    ],
    "stateMutability": "nonpayable",
    "type": "function"
  },
  {
    "inputs": [
      {
        "internalType": "address",
        "name": "sender",
        "type": "address"
      },
      {
        "internalType": "uint256",
        "name": "amount",
        "type": "uint256"
      }
    ],
    "name": "burnFrom",
    "outputs": [
      {
        "internalType": "bool",
        "name": "",
        "type": "bool"
      }
    ],
    "stateMutability": "nonpayable",
    "type": "function"
  },
  {
    "inputs": [],
    "name": "decimals",
    "outputs": [
      {
        "internalType": "uint8",
        "name": "",
        "type": "uint8"
      }
    ],
    "stateMutability": "pure",
    "type": "function"
  },
  {
    "inputs": [
      {
        "internalType": "address",
        "name": "spender",
        "type": "address"
      },
      {
        "internalType": "uint256",
        "name": "subtractedValue",
        "type": "uint256"
      }
    ],
    "name": "decreaseAllowance",
    "outputs": [
      {
        "internalType": "bool",
        "name": "",
        "type": "bool"
      }
    ],
    "stateMutability": "nonpayable",
    "type": "function"
  },
  {
    "inputs": [],
    "name": "deposit",
    "outputs": [],
    "stateMutability": "payable",
    "type": "function"
  },
  {
    "inputs": [
      {
        "internalType": "address",
        "name": "account",
        "type": "address"
      }
    ],
    "name": "getAccount",
    "outputs": [
      {
        "internalType": "bool",
        "name": "isHolder",
        "type": "bool"
      },
      {
        "internalType": "bool",
        "name": "isWhale",
        "type": "bool"
      },
      {
        "internalType": "bool",
        "name": "isFlat",
        "type": "bool"
      },
      {
        "internalType": "bool",
        "name": "isSlot",
        "type": "bool"
      },
      {
        "internalType": "string",
        "name": "username",
        "type": "string"
      },
      {
        "internalType": "uint256",
        "name": "balance",
        "type": "uint256"
      },
      {
        "internalType": "uint256",
        "name": "harvest",
        "type": "uint256"
      },
      {
        "internalType": "uint256",
        "name": "totalHarvest",
        "type": "uint256"
      },
      {
        "internalType": "uint256",
        "name": "totalTaxSnap",
        "type": "uint256"
      },
      {
        "internalType": "uint256",
        "name": "bnbBalance",
        "type": "uint256"
      },
      {
        "internalType": "uint256",
        "name": "presaleDeposit",
        "type": "uint256"
      },
      {
        "internalType": "uint256",
        "name": "presalePortion",
        "type": "uint256"
      },
      {
        "internalType": "bool",
        "name": "presaleRedeemed",
        "type": "bool"
      }
    ],
    "stateMutability": "view",
    "type": "function"
  },
  {
    "inputs": [
      {
        "internalType": "string",
        "name": "value",
        "type": "string"
      }
    ],
    "name": "getAccountByUsername",
    "outputs": [
      {
        "internalType": "address",
        "name": "account",
        "type": "address"
      },
      {
        "internalType": "bool",
        "name": "isHolder",
        "type": "bool"
      },
      {
        "internalType": "bool",
        "name": "isWhale",
        "type": "bool"
      },
      {
        "internalType": "bool",
        "name": "isFlat",
        "type": "bool"
      },
      {
        "internalType": "bool",
        "name": "isSlot",
        "type": "bool"
      },
      {
        "internalType": "string",
        "name": "username",
        "type": "string"
      },
      {
        "internalType": "uint256",
        "name": "balance",
        "type": "uint256"
      },
      {
        "internalType": "uint256",
        "name": "harvest",
        "type": "uint256"
      },
      {
        "internalType": "uint256",
        "name": "totalHarvest",
        "type": "uint256"
      },
      {
        "internalType": "uint256",
        "name": "totalTaxSnap",
        "type": "uint256"
      }
    ],
    "stateMutability": "view",
    "type": "function"
  },
  {
    "inputs": [],
    "name": "getGlobal",
    "outputs": [
      {
        "internalType": "bool",
        "name": "autoSwapReady",
        "type": "bool"
      },
      {
        "internalType": "address",
        "name": "fomoNext",
        "type": "address"
      },
      {
        "internalType": "uint16[7]",
        "name": "i16",
        "type": "uint16[7]"
      },
      {
        "internalType": "uint256[17]",
        "name": "i256",
        "type": "uint256[17]"
      },
      {
        "internalType": "uint8[8]",
        "name": "takerFees",
        "type": "uint8[8]"
      },
      {
        "internalType": "uint8[8]",
        "name": "makerFees",
        "type": "uint8[8]"
      },
      {
        "internalType": "uint8[8]",
        "name": "whaleFees",
        "type": "uint8[8]"
      },
      {
        "internalType": "uint8[8]",
        "name": "robberFees",
        "type": "uint8[8]"
      },
      {
        "internalType": "address[]",
        "name": "flats",
        "type": "address[]"
      },
      {
        "internalType": "address[]",
        "name": "slots",
        "type": "address[]"
      }
    ],
    "stateMutability": "view",
    "type": "function"
  },
  {
    "inputs": [
      {
        "internalType": "uint256",
        "name": "offset",
        "type": "uint256"
      }
    ],
    "name": "getHolders",
    "outputs": [
      {
        "internalType": "uint256[100]",
        "name": "ids",
        "type": "uint256[100]"
      },
      {
        "internalType": "address[100]",
        "name": "holders",
        "type": "address[100]"
      },
      {
        "internalType": "string[100]",
        "name": "usernames",
        "type": "string[100]"
      },
      {
        "internalType": "uint256[100]",
        "name": "balances",
        "type": "uint256[100]"
      },
      {
        "internalType": "bool[100]",
        "name": "isWhales",
        "type": "bool[100]"
      }
    ],
    "stateMutability": "view",
    "type": "function"
  },
  {
    "inputs": [],
    "name": "getMetadata",
    "outputs": [
      {
        "internalType": "string[3]",
        "name": "tokenNames",
        "type": "string[3]"
      },
      {
        "internalType": "string[3]",
        "name": "tokenSymbols",
        "type": "string[3]"
      },
      {
        "internalType": "uint8[3]",
        "name": "tokenDecimals",
        "type": "uint8[3]"
      },
      {
        "internalType": "uint256[3]",
        "name": "tokenPrices",
        "type": "uint256[3]"
      },
      {
        "internalType": "uint256[9]",
        "name": "supplies",
        "type": "uint256[9]"
      },
      {
        "internalType": "address[9]",
        "name": "accounts",
        "type": "address[9]"
      },
      {
        "internalType": "uint256",
        "name": "holders",
        "type": "uint256"
      },
      {
        "internalType": "uint256",
        "name": "usernames",
        "type": "uint256"
      }
    ],
    "stateMutability": "view",
    "type": "function"
  },
  {
    "inputs": [
      {
        "internalType": "address",
        "name": "account",
        "type": "address"
      }
    ],
    "name": "getPresale",
    "outputs": [
      {
        "internalType": "bool",
        "name": "depositAllowed",
        "type": "bool"
      },
      {
        "internalType": "uint256",
        "name": "depositCap",
        "type": "uint256"
      },
      {
        "internalType": "uint32",
        "name": "startTimestamp",
        "type": "uint32"
      },
      {
        "internalType": "uint32",
        "name": "endTimestamp",
        "type": "uint32"
      },
      {
        "internalType": "uint256",
        "name": "liquidityCreatedTimestamp",
        "type": "uint256"
      },
      {
        "internalType": "uint256",
        "name": "presaleAmount",
        "type": "uint256"
      },
      {
        "internalType": "uint256",
        "name": "fund",
        "type": "uint256"
      },
      {
        "internalType": "uint256",
        "name": "portion",
        "type": "uint256"
      },
      {
        "internalType": "bool",
        "name": "redeemed",
        "type": "bool"
      }
    ],
    "stateMutability": "view",
    "type": "function"
  },
  {
    "inputs": [
      {
        "internalType": "address",
        "name": "account",
        "type": "address"
      }
    ],
    "name": "harvestOf",
    "outputs": [
      {
        "internalType": "uint256",
        "name": "",
        "type": "uint256"
      }
    ],
    "stateMutability": "view",
    "type": "function"
  },
  {
    "inputs": [
      {
        "internalType": "address",
        "name": "spender",
        "type": "address"
      },
      {
        "internalType": "uint256",
        "name": "addedValue",
        "type": "uint256"
      }
    ],
    "name": "increaseAllowance",
    "outputs": [
      {
        "internalType": "bool",
        "name": "",
        "type": "bool"
      }
    ],
    "stateMutability": "nonpayable",
    "type": "function"
  },
  {
    "inputs": [],
    "name": "name",
    "outputs": [
      {
        "internalType": "string",
        "name": "",
        "type": "string"
      }
    ],
    "stateMutability": "pure",
    "type": "function"
  },
  {
    "inputs": [],
    "name": "owner",
    "outputs": [
      {
        "internalType": "address",
        "name": "",
        "type": "address"
      }
    ],
    "stateMutability": "view",
    "type": "function"
  },
  {
    "inputs": [
      {
        "internalType": "uint256",
        "name": "tax",
        "type": "uint256"
      },
      {
        "internalType": "uint256",
        "name": "airdrop",
        "type": "uint256"
      },
      {
        "internalType": "uint256",
        "name": "fomo",
        "type": "uint256"
      },
      {
        "internalType": "uint256",
        "name": "liquidity",
        "type": "uint256"
      },
      {
        "internalType": "uint256",
        "name": "fund",
        "type": "uint256"
      },
      {
        "internalType": "uint256",
        "name": "destroy",
        "type": "uint256"
      }
    ],
    "name": "payFee",
    "outputs": [
      {
        "internalType": "bool",
        "name": "",
        "type": "bool"
      }
    ],
    "stateMutability": "nonpayable",
    "type": "function"
  },
  {
    "inputs": [
      {
        "internalType": "address",
        "name": "sender",
        "type": "address"
      },
      {
        "internalType": "uint256",
        "name": "tax",
        "type": "uint256"
      },
      {
        "internalType": "uint256",
        "name": "airdrop",
        "type": "uint256"
      },
      {
        "internalType": "uint256",
        "name": "fomo",
        "type": "uint256"
      },
      {
        "internalType": "uint256",
        "name": "liquidity",
        "type": "uint256"
      },
      {
        "internalType": "uint256",
        "name": "fund",
        "type": "uint256"
      },
      {
        "internalType": "uint256",
        "name": "destroy",
        "type": "uint256"
      }
    ],
    "name": "payFeeFrom",
    "outputs": [
      {
        "internalType": "bool",
        "name": "",
        "type": "bool"
      }
    ],
    "stateMutability": "nonpayable",
    "type": "function"
  },
  {
    "inputs": [],
    "name": "presaleRedeem",
    "outputs": [],
    "stateMutability": "nonpayable",
    "type": "function"
  },
  {
    "inputs": [
      {
        "internalType": "address",
        "name": "account",
        "type": "address"
      }
    ],
    "name": "registerSlot",
    "outputs": [],
    "stateMutability": "nonpayable",
    "type": "function"
  },
  {
    "inputs": [
      {
        "internalType": "string",
        "name": "value",
        "type": "string"
      }
    ],
    "name": "setUsername",
    "outputs": [],
    "stateMutability": "nonpayable",
    "type": "function"
  },
  {
    "inputs": [],
    "name": "symbol",
    "outputs": [
      {
        "internalType": "string",
        "name": "",
        "type": "string"
      }
    ],
    "stateMutability": "pure",
    "type": "function"
  },
  {
    "inputs": [],
    "name": "takeHarvest",
    "outputs": [
      {
        "internalType": "bool",
        "name": "",
        "type": "bool"
      }
    ],
    "stateMutability": "nonpayable",
    "type": "function"
  },
  {
    "inputs": [],
    "name": "totalSupply",
    "outputs": [
      {
        "internalType": "uint256",
        "name": "",
        "type": "uint256"
      }
    ],
    "stateMutability": "view",
    "type": "function"
  },
  {
    "inputs": [
      {
        "internalType": "address",
        "name": "recipient",
        "type": "address"
      },
      {
        "internalType": "uint256",
        "name": "amount",
        "type": "uint256"
      }
    ],
    "name": "transfer",
    "outputs": [
      {
        "internalType": "bool",
        "name": "",
        "type": "bool"
      }
    ],
    "stateMutability": "nonpayable",
    "type": "function"
  },
  {
    "inputs": [
      {
        "internalType": "address",
        "name": "sender",
        "type": "address"
      },
      {
        "internalType": "address",
        "name": "recipient",
        "type": "address"
      },
      {
        "internalType": "uint256",
        "name": "amount",
        "type": "uint256"
      }
    ],
    "name": "transferFrom",
    "outputs": [
      {
        "internalType": "bool",
        "name": "",
        "type": "bool"
      }
    ],
    "stateMutability": "nonpayable",
    "type": "function"
  },
  {
    "inputs": [
      {
        "internalType": "address",
        "name": "newOwner",
        "type": "address"
      }
    ],
    "name": "transferOwnership",
    "outputs": [],
    "stateMutability": "nonpayable",
    "type": "function"
  },
  {
    "stateMutability": "payable",
    "type": "receive"
  }
]
